odoo/addons/l10n_it_currency_rate_update_boi/README.rst
odoo/addons/l10n_it_currency_rate_update_boi/__init__.py
odoo/addons/l10n_it_currency_rate_update_boi/__manifest__.py
odoo/addons/l10n_it_currency_rate_update_boi/hooks.py
odoo/addons/l10n_it_currency_rate_update_boi/i18n/currency_rate_update_boi.pot
odoo/addons/l10n_it_currency_rate_update_boi/i18n/it.po
odoo/addons/l10n_it_currency_rate_update_boi/i18n/l10n_it_currency_rate_update_boi.pot
odoo/addons/l10n_it_currency_rate_update_boi/migrations/18.0.1.0.0/pre-migrate.py
odoo/addons/l10n_it_currency_rate_update_boi/models/__init__.py
odoo/addons/l10n_it_currency_rate_update_boi/models/res_currency_rate_provider_BOI.py
odoo/addons/l10n_it_currency_rate_update_boi/readme/CONFIGURE.md
odoo/addons/l10n_it_currency_rate_update_boi/readme/CONTRIBUTORS.md
odoo/addons/l10n_it_currency_rate_update_boi/readme/DESCRIPTION.md
odoo/addons/l10n_it_currency_rate_update_boi/static/description/icon.png
odoo/addons/l10n_it_currency_rate_update_boi/static/description/index.html
odoo/addons/l10n_it_currency_rate_update_boi/tests/__init__.py
odoo/addons/l10n_it_currency_rate_update_boi/tests/test_currency_rate_update_boi.py
odoo_addon_l10n_it_currency_rate_update_boi-18.0.1.0.0.4.dist-info/METADATA
odoo_addon_l10n_it_currency_rate_update_boi-18.0.1.0.0.4.dist-info/WHEEL
odoo_addon_l10n_it_currency_rate_update_boi-18.0.1.0.0.4.dist-info/top_level.txt
odoo_addon_l10n_it_currency_rate_update_boi-18.0.1.0.0.4.dist-info/RECORD
