Metadata-Version: 2.1
Name: odoo-addon-l10n_it_currency_rate_update_boi
Version: 18.0.1.0.0.4
Requires-Python: >=3.10
Requires-Dist: odoo-addon-currency_rate_update==18.0.*
Requires-Dist: odoo==18.0.*
Summary: Update exchange rates using www.bancaditalia.it
Home-page: https://github.com/OCA/l10n-italy
License: AGPL-3
Author: TAKOBI, Odoo Community Association (OCA)
Author-email: support@odoo-community.org
Classifier: Programming Language :: Python
Classifier: Framework :: Odoo
Classifier: Framework :: Odoo :: 18.0
Classifier: License :: OSI Approved :: GNU Affero General Public License v3
